<?xml version="1.0" encoding="UTF-8"?>
<!-- this section has overriding strategy, the attributes mentioned here 
	will only be overriden -->
<banner>
	<top-banner>
		<!-- <li data-transition="3dcurtain-vertical" data-slotamount="7" data-masterspeed="500" 
			> <img src="slide1.jpg" alt="slidebg1" data-bgfit="cover" data-bgposition="left 
			top" data-bgrepeat="no-repeat" /> <div class="tp-caption lfl" data-x="-20" 
			data-y="12" data-speed="2000" data-start="800" data-easing="Back.easeOut" 
			data-endspeed="500" data-captionhidden="on" style="font-size:40px; z-index: 
			4"><span><img src="boy.png" alt="" /></span></div> <div class="tp-caption 
			lfr" data-x="290" data-y="12" data-speed="2000" data-start="800" data-easing="Back.easeOut" 
			data-endspeed="500" data-captionhidden="on" style="font-size:40px; z-index: 
			4"><span><img style="z-index:0;" src="girl1.png" alt="" /></span></div> <div 
			class="tp-caption lfb" data-x="150" data-y="12" data-speed="2000" data-start="800" 
			data-easing="Back.easeOut" data-endspeed="500" data-captionhidden="on" style="font-size:40px; 
			z-index: 4"><span><img src="girl2.png" alt="" /></span></div> <div class="tp-caption 
			lft" data-x="640" data-y="230" data-speed="2000" data-start="800" data-easing="Back.easeOut" 
			data-endspeed="500" data-captionhidden="on" style="font-size:40px; z-index: 
			4"><span><img src="box1.png" alt="" /></span></div> <div class="tp-caption 
			lfb" data-x="1045" data-y="400" data-speed="2000" data-start="800" data-easing="Back.easeOut" 
			data-endspeed="500" data-captionhidden="on" style="font-size:40px; z-index: 
			4"><span><img src="box2.png" alt="" /></span></div> <div class="tp-caption 
			skewfromright" data-x="670" data-y="205" data-speed="2000" data-start="800" 
			data-easing="Back.easeOut" data-endspeed="500" data-captionhidden="on" style=""><h2 
			class="slide4-text1">More then <i>branding</i> agancy</h2></div> <div class="tp-caption 
			skewfromleft" data-x="670" data-y="250" data-speed="2000" data-start="800" 
			data-easing="Back.easeOut" data-endspeed="500" data-captionhidden="on" style="z-index:8;"><h2 
			class="slide4-text2">Discover more about store Advanced Technology</h2></div> 
			<div class="tp-caption skewfromright" data-x="670" data-y="290" data-speed="2000" 
			data-start="800" data-easing="Back.easeOut" data-endspeed="500" data-captionhidden="on" 
			style="z-index:8;"><p class="slide4-text3">Sed eget tellus sapien. Proinupmoso 
			etiamgo velmis dolor amet pPro-<br/>inupmoso etiamgo velmis dolor amet promo 
			elit.</p></div> <div class="tp-caption skewfromright" data-x="670" data-y="360" 
			data-speed="2000" data-start="800" data-easing="Back.easeOut" data-endspeed="500" 
			data-captionhidden="on" style="font-size:40px; z-index: 4"><a href="#" title="" 
			class="slide2-btn">Purchase on Themeforest</a></div> </li> <li data-transition="slotzoom-horizontal" 
			data-slotamount="7" data-masterspeed="500" > <img src="slide2.jpg" alt="slidebg1" 
			data-bgfit="cover" data-bgposition="left top" data-bgrepeat="no-repeat" /> 
			<div class="tp-caption skewfromleft" data-x="292" data-y="196" data-speed="1500" 
			data-start="800" data-easing="SlowMo.ease" data-endspeed="500" data-captionhidden="on" 
			style="font-size:40px; z-index: 4"><span class="slide-text1">Shop<i>inn</i></span></div> 
			<div class="tp-caption skewfromright" data-x="158" data-y="244" data-speed="1500" 
			data-start="800" data-easing="Sine.easeInOut" data-endspeed="500" data-captionhidden="on" 
			style="font-size:30px; z-index: 4"><span class="slide-text1">More then branding 
			<i>agency</i></span></div> <div class="tp-caption fade" data-x="193" data-y="285" 
			data-speed="1500" data-start="800" data-easing="Circ.easeIn" data-endspeed="500" 
			data-captionhidden="on" style="font-size:14px; z-index: 4"><span class="slide-text1"><i>Discover 
			more about store Advanced Technology</i></span></div> <div class="tp-caption 
			sfr" data-x="314" data-y="326" data-speed="1000" data-start="800" data-easing="easeInBounce" 
			data-endspeed="500" data-captionhidden="on" style="font-size:14px; z-index: 
			4"><a class="slide-text1-btn" href="#" title="">VIEW MORE</a></div> <div 
			class="tp-caption lfr" data-x="723" data-y="88" data-speed="1500" data-start="800" 
			data-easing="Back.easeOut" data-endspeed="500" data-captionhidden="on" style="z-index: 
			4;"><img src="slide-hand.png" alt="" /></div> </li> <li data-transition="curtain-2" 
			data-slotamount="7" data-masterspeed="500" > <img src="slide3.jpg" alt="slidebg1" 
			data-bgfit="cover" data-bgposition="left top" data-bgrepeat="no-repeat" /> 
			<div class="tp-caption skewfromleft" data-x="2" data-y="141" data-speed="2000" 
			data-start="1200" data-easing="Back.easeOut" data-endspeed="500" data-captionhidden="on" 
			style="z-index: 4"><span><img src="slide-girl.png" alt="" /></span></div> 
			<div class="tp-caption skewfromright" data-x="650" data-y="162" data-speed="2000" 
			data-start="800" data-easing="Back.easeOut" data-endspeed="500" data-captionhidden="on" 
			style="font-size:40px; z-index: 4; font-size:40px;"><span class="slide2-text1">SHOPPING</span></div> 
			<div class="tp-caption skewfromleft" data-x="650" data-y="224" data-speed="2000" 
			data-start="800" data-easing="Back.easeOut" data-endspeed="500" data-captionhidden="on" 
			style="font-size:40px; z-index: 4"><span class="slide2-text2">More then branding 
			agency</span></div> <div class="tp-caption skewfromright" data-x="650" data-y="294" 
			data-speed="2000" data-start="800" data-easing="Back.easeOut" data-endspeed="500" 
			data-captionhidden="on" style="font-size:40px; z-index: 4; font-size:30px;"><span 
			class="slide2-text1">More then branding</span></div> <div class="tp-caption 
			skewfromleft " data-x="650" data-y="375" data-speed="2000" data-start="800" 
			data-easing="Back.easeOut" data-endspeed="500" data-captionhidden="on" style="font-size:40px; 
			z-index: 4"><a href="#" title="" class="slide2-btn">Purchase on Themeforest</a></div> 
			</li> <li data-transition="boxslide" data-slotamount="7" data-masterspeed="500" 
			> <img src="slide4.jpg" alt="slidebg1" data-bgfit="cover" data-bgposition="left 
			top" data-bgrepeat="no-repeat" /> <div class="tp-caption lfb" data-x="2" 
			data-y="2" data-speed="2000" data-start="800" data-easing="Power0.easeIn" 
			data-endspeed="500" data-captionhidden="on" style="font-size:40px; z-index: 
			4"><span><img src="balloons.png" alt="" /></span></div> <div class="tp-caption 
			skewfromleft" data-x="680" data-y="210" data-speed="2000" data-start="800" 
			data-easing="Back.easeOut" data-endspeed="500" data-captionhidden="on" style="font-size:40px; 
			z-index: 4"><h2 class="slide3-text1"> our most complete <i>WooCommerce</i> 
			theme yet!</h2></div> <div class="tp-caption skewfromright" data-x="680" 
			data-y="252" data-speed="2000" data-start="800" data-easing="Back.easeOut" 
			data-endspeed="500" data-captionhidden="on" style="font-size:40px; z-index: 
			4"> <ul class="slide3-list"> <li><i class="fa fa-bitbucket"></i><span>Truly 
			Fantastic Theme For Your Shop Venture</span></li> <li><i class="fa fa-shopping-cart"></i><span>Buy 
			It Now! Fantastic Deals</span></li> <li><i class="fa fa-thumb-tack"></i><span>For 
			More Information Call +386 40 000 1111 now!</span></li> <li><i class="fa 
			fa-lightbulb-o"></i><span>Buy It On Themeforest For Only $55</span></li> 
			</ul> </div> <div class="tp-caption" data-x="-20" data-y="95" data-speed="500" 
			data-start="800" data-easing="Back.easeOut" data-endspeed="500" data-captionhidden="on" 
			style="font-size:40px; z-index: 4"><span><img src="slide-mobile.png" alt="" 
			/></span></div> </li> -->

	</top-banner>
</banner>	